p2pnet/__init__.py
p2pnet/crypto.py
p2pnet/discovery.py
p2pnet/send_ping.py
p2pnet-0.0.1.dist-info/METADATA
p2pnet-0.0.1.dist-info/RECORD
p2pnet-0.0.1.dist-info/WHEEL
p2pnet-0.0.1.dist-info/top_level.txt
