Metadata-Version: 2.1
Name: p2pnet
Version: 0.0.1
Summary: RLP-encoded p2p networking using BLS signatures
Home-page: https://github.com/rosendin/p2pnet
Author: Matthew Rosendin
Author-email: matthew.rosendin@gmail.com
License: BSD
Download-URL: https://github.com/rosendin/pyeth/tarball/0.0.1
Platform: UNKNOWN
Classifier: Intended Audience :: Developers
Classifier: Programming Language :: Python :: 3
Requires-Dist: arrow (==0.10.0)
Requires-Dist: binaryornot (==0.4.3)
Requires-Dist: cffi (==1.10.0)
Requires-Dist: chardet (==3.0.4)
Requires-Dist: click (==6.7)
Requires-Dist: cookiecutter (==1.5.1)
Requires-Dist: future (==0.16.0)
Requires-Dist: ipaddress (==1.0.18)
Requires-Dist: Jinja2 (==2.9.6)
Requires-Dist: jinja2-time (==0.2.0)
Requires-Dist: MarkupSafe (==1.0)
Requires-Dist: nose (==1.3.7)
Requires-Dist: poyo (==0.4.1)
Requires-Dist: pycparser (==2.18)
Requires-Dist: pysha3 (==1.0.2)
Requires-Dist: python-dateutil (==2.6.1)
Requires-Dist: rlp (==0.5.1)
Requires-Dist: secp256k1 (==0.13.2)
Requires-Dist: six (==1.10.0)
Requires-Dist: whichcraft (==0.4.1)
